functions_by_alpkocer3/README.md
functions_by_alpkocer3/math_functions.py
functions_by_alpkocer3_py-0.3.0.dist-info/WHEEL
functions_by_alpkocer3_py-0.3.0.dist-info/METADATA
functions_by_alpkocer3_py-0.3.0.dist-info/RECORD
