Metadata-Version: 2.1
Name: functions-by-alpkocer3-py
Version: 0.3.0
Summary: Test Project
Author: Alp Kocer
Author-email: gokalpkocer@gmail.com
Requires-Python: >=3.10,<4.0
Classifier: Programming Language :: Python :: 3
Classifier: Programming Language :: Python :: 3.10
Classifier: Programming Language :: Python :: 3.11
